setup.py
cubes/__init__.py
cubes/auth.py
cubes/browser.py
cubes/calendar.py
cubes/cells.py
cubes/common.py
cubes/compat.py
cubes/computation.py
cubes/datastructures.py
cubes/errors.py
cubes/ext.py
cubes/formatters.py
cubes/localization.py
cubes/logging.py
cubes/mapper.py
cubes/metadata.py
cubes/model.py
cubes/namespace.py
cubes/providers.py
cubes/statutils.py
cubes/stores.py
cubes/workspace.py
cubes.egg-info/PKG-INFO
cubes.egg-info/SOURCES.txt
cubes.egg-info/dependency_links.txt
cubes.egg-info/entry_points.txt
cubes.egg-info/requires.txt
cubes.egg-info/top_level.txt
cubes/schemas/cube.json
cubes/schemas/dimension.json
cubes/schemas/model.json
cubes/server/__init__.py
cubes/server/app.py
cubes/server/auth.py
cubes/server/base.py
cubes/server/blueprint.py
cubes/server/browser.py
cubes/server/caching.py
cubes/server/decorators.py
cubes/server/errors.py
cubes/server/local.py
cubes/server/logging.py
cubes/server/store.py
cubes/server/utils.py
cubes/server/templates/index.html
cubes/slicer/__init__.py
cubes/slicer/commands.py
cubes/sql/__init__.py
cubes/sql/browser.py
cubes/sql/expressions.py
cubes/sql/functions.py
cubes/sql/logging.py
cubes/sql/mapper.py
cubes/sql/query.py
cubes/sql/store.py
cubes/sql/utils.py
cubes/templates/cross_table.html
cubes/templates/simple_table.html
cubes/tutorial/__init__.py
cubes/tutorial/sql.py