Metadata-Version: 1.1
Name: cubes
Version: 1.1
Summary: Lightweight framework for Online Analytical Processing (OLAP) and multidimensional analysis
Home-page: http://cubes.databrewery.org
Author: Stefan Urbanek
Author-email: stefan.urbanek@gmail.com
License: MIT license with following addition: If your version of the Software supports interaction with it remotely through a computer network, the above copyright notice and this permission notice shall be accessible to all users.
Keywords: olap multidimensional data analysis
Platform: UNKNOWN
Classifier: Development Status :: 5 - Production/Stable
Classifier: Intended Audience :: Developers
Classifier: Intended Audience :: Science/Research
Classifier: License :: OSI Approved :: MIT License
Classifier: Programming Language :: Python :: 3
Classifier: Programming Language :: Python
Classifier: Topic :: Database
Classifier: Topic :: Scientific/Engineering
Classifier: Topic :: Utilities
